MANIFEST.in
README.rst
requirements.txt
setup.py
cnml/__init__.py
cnml/_version.py
cnml/spline.py
cnml/woe.py
cnml.egg-info/PKG-INFO
cnml.egg-info/SOURCES.txt
cnml.egg-info/dependency_links.txt
cnml.egg-info/requires.txt
cnml.egg-info/top_level.txt
tests/__init__.py
tests/conftest.py
tests/test_spline.py
tests/test_woe.py
tests/test-files/titanic/gender_submission.csv
tests/test-files/titanic/test.csv
tests/test-files/titanic/train.csv